MANIFEST.in
setup.cfg
setup.py
docs/README.md
docs/README.rst
eZadb.egg-info/PKG-INFO
eZadb.egg-info/SOURCES.txt
eZadb.egg-info/dependency_links.txt
eZadb.egg-info/entry_points.txt
eZadb.egg-info/not-zip-safe
eZadb.egg-info/requires.txt
eZadb.egg-info/top_level.txt
ezadb/EzADB.py
ezadb/__init__.py
ezadb/__main__.py
ezadb/ezadb_cmd.py
ezadb/conf/Config.py
ezadb/conf/ConfigManager.py
ezadb/conf/I18n.py
ezadb/conf/SystemUtils.py
ezadb/conf/__init__.py
ezadb/gui/EzADBGui.py
ezadb/gui/EzADBGui.pyc
ezadb/gui/PreviewImageDialog.py
ezadb/gui/PreviewImageDialog.pyc
ezadb/gui/__init__.py
ezadb/gui/__init__.pyc
ezadb/gui/about_dialog.ui
ezadb/gui/appinfo_dialog.ui
ezadb/gui/design_main.ui
ezadb/gui/progress_dialog.ui
ezadb/images/ezadb.gif
ezadb/locale/pt/LC_MESSAGES/ezadb.mo
ezadb/locale/pt/LC_MESSAGES/ezadb.po
ezadb/utils/Log.py
ezadb/utils/Utils.py
ezadb/utils/__init__.py