Metadata-Version: 1.2
Name: eZadb
Version: 1.1.0
Summary: ezADB - Easy Android Debug Bridge. Use adb like a boss!
Home-page: https://filipebatista.github.io/eZadb
Author: Filipe Baptista
Author-email: filipe.batista@outlook.com
License: GPL-3.0
Keywords: android adb android-debug-bridge development
Platform: UNKNOWN
Classifier: Development Status :: 3 - Alpha
Classifier: Intended Audience :: Developers
Classifier: License :: OSI Approved :: GNU General Public License v3 (GPLv3)
Classifier: Programming Language :: Python
Requires-Python: >=2.7
